zohoreader/__init__.py
zohoreader/zohoreader.py
zohoreader-0.1.1.dist-info/DESCRIPTION.rst
zohoreader-0.1.1.dist-info/METADATA
zohoreader-0.1.1.dist-info/RECORD
zohoreader-0.1.1.dist-info/WHEEL
zohoreader-0.1.1.dist-info/metadata.json
zohoreader-0.1.1.dist-info/top_level.txt
